Workbook

Sheet Detalle de Costos
D3: Costos por paquete de trabajo
A5: Nombre del Proyecto | E5: Segmentación de mercado para Targeting
A6: Código | B6: SMT-2026-01
A8: EDT / Paquete de Trabajo | C8: Sem 1 | D8: Sem 2 | E8: Sem 3 | F8: Sem 4 | G8: Sem 5 | H8: Sem 6 | I8: Sem 7 | J8: Sem 8 | K8: Sem 9 | L8: Sem 10 | M8: Sem 11 | N8: Sem 12 | O8: TOTAL | P8: 14 | Q8: 15 | R8: 16 | S8: 17 | T8: 18 | U8: 19 | V8: 20 | W8: 21 | X8: 22 | Y8: 23 | Z8: 24 | AA8: 25 | AB8: 26 | AC8: 27 | AD8: 28 | AE8: 29 | AF8: 30 | AG8: 31 | AH8: 32 | AI8: 33 | AJ8: 34 | AK8: 35 | AL8: 36 | AM8: 37 | AN8: 38 | AO8: 39 | AP8: 40 | AQ8: 41 | AR8: 42 | AS8: 43 | AT8: 44 | AU8: 45 | AV8: 46 | AW8: 47 | AX8: 48 | AY8: 49 | AZ8: 50 | BA8: 51 | BB8: 52 | BC8: 53 | BD8: 54 | BE8: 55 | BF8: 56 | BG8: 57 | BH8: 58 | BI8: 59 | BJ8: 60
A9: 1 – Gestión Integral del Proyecto
A10: 1.1.1 | B10: Tablero Kanban de sprints | O10: =SUM(C10:N10) -> 0
A11: 1.1.2 | B11: Bitácora de decisiones y cambios | D11: - | E11: - | F11: - | G11: - | H11: - | I11: - | J11: - | K11: - | L11: - | M11: - | N11: - | O11: =SUM(C11:N11) -> 0
A12: 1.1.3 | B12: Repositorio de documentos | C12: 1553 | D12: 1553 | E12: 1553 | F12: 1553 | G12: 1553 | H12: 1553 | I12: 1553 | J12: 1553 | O12: =SUM(C12:N12) -> 12424
A13: 2 – Análisis Exploratorio de Datos (EDA) | C13: 1553 | D13: $1,553 | E13: 1600 | F13: 1600 | G13: $1,553 | H13: $1,553 | I13: $1,553 | J13: $1,553 | K13: 1553
A14: 2.1.1 | B14: Reporte de calidad de datos | F14: 1553 | J14: 1553 | O14: =SUM(C14:N14) -> 3106
A15: 2.1.2.1 | B15: Histogramas de distribución | C15: =15528-1553 -> 13975 | D15: - | E15: - | F15: - | G15: - | H15: - | I15: - | J15: - | K15: - | L15: - | M15: - | N15: - | O15: =SUM(C15:N15) -> 13975
A16: 2.1.2.2 | B16: Scatter plot de ingresos vs gasto | C16: - | F16: - | G16: - | H16: - | I16: - | K16: - | L16: - | M16: - | N16: - | O16: =SUM(C16:N16) -> 0
A17: 2.1.2.3 | B17: Heatmap de correlación | C17: - | D17: - | E17: - | F17: 21739 | H17: 21739 | I17: 21739 | J17: 21739 | K17: 21739 | L17: - | M17: - | N17: - | O17: =SUM(C17:N17) -> 108695
A18: 2.1.3 | B18: Análisis de patrones preliminares | O18: =SUM(C18:N18) -> 0
A19: 3 – Modelo de Segmentación | C19: - | D19: - | E19: - | F19: - | G19: 21739 | H19: - | I19: - | J19: - | K19: - | L19: - | M19: - | N19: - | O19: =SUM(C19:N19) -> 21739
A20: 3.1.1.1 | B20: Preprocesamiento de datos | C20: - | D20: - | E20: - | F20: - | G20: - | H20: 15528 | I20: - | J20: - | K20: - | L20: - | M20: - | N20: - | O20: =SUM(C20:N20) -> 15528
A21: 3.1.1.2 | B21: Implementación K-means | C21: - | D21: - | E21: - | F21: - | G21: - | H21: - | I21: 15528 | J21: - | K21: - | L21: - | M21: - | N21: - | O21: =SUM(C21:N21) -> 15528
A22: 3.1.1.3 | B22: Implementación Hierarchical Clustering | C22: - | D22: - | E22: - | F22: - | G22: - | H22: - | I22: - | J22: 15528 | K22: - | L22: - | M22: - | N22: - | O22: =SUM(C22:N22) -> 15528
A23: 3.1.2 | B23: Validación cualitativa de clusters | C23: - | D23: - | E23: - | F23: - | G23: - | H23: - | I23: - | J23: - | K23: 9317 | L23: - | M23: - | N23: - | O23: =SUM(C23:N23) -> 9317
A24: 3.1.3 | B24: Selección del modelo óptimo | O24: =SUM(C24:N24) -> 0
A25: 4 – Caracterización de Segmentos | C25: - | D25: - | E25: - | F25: - | G25: - | H25: - | I25: - | J25: - | K25: - | M25: - | N25: - | O25: =SUM(C25:N25) -> 0
A26: 4.1.1.1 | B26: Estadísticas descriptivas por cluster | C26: - | D26: - | E26: - | F26: - | G26: - | H26: - | I26: - | J26: - | K26: - | L26: 15528 | M26: - | N26: - | O26: =SUM(C26:N26) -> 15528
A27: 4.2 | B27: Comportamiento de compra | C27: - | D27: - | E27: - | F27: - | G27: - | H27: - | I27: - | J27: - | K27: - | L27: - | N27: - | O27: =SUM(C27:N27) -> 0
A28: 4.3 | B28: Sizing de mercado | O28: =SUM(C28:N28) -> 0
A29: 5 – Estrategia Comercial y Visualización | C29: - | D29: - | E29: - | F29: - | G29: - | H29: - | I29: - | J29: - | K29: - | N29: - | O29: =SUM(C29:N29) -> 0
A30: 5.1.1.1 | B30: Wireframe del dashboard | C30: - | D30: - | E30: - | F30: - | G30: - | H30: - | I30: - | J30: - | K30: - | L30: 12422 | O30: =SUM(C30:N30) -> 12422
A31: 5.1.1.2 | B31: Implementación interactiva | C31: - | D31: - | E31: - | F31: - | G31: - | H31: - | I31: - | J31: - | K31: - | L31: - | M31: - | O31: =SUM(C31:N31) -> 0
A32: 5.1.2 | B32: Gráficos de perfil comparativo | C32: - | D32: - | E32: - | F32: - | G32: - | H32: - | I32: - | J32: - | K32: - | L32: - | N32: - | O32: =SUM(C32:N32) -> 0
A33: 5.2.1 | B33: Recomendaciones de targeting | C33: - | D33: - | E33: - | F33: - | G33: - | H33: - | I33: - | J33: - | K33: - | L33: - | M33: - | O33: =SUM(C33:N33) -> 0
A34: 5.2.2 | B34: Asignación sugerida de recursos | O34: =SUM(C34:N34) -> 0
A35: 6 – Cierre y Entrega Final | C35: - | D35: - | E35: - | F35: - | G35: - | H35: - | I35: - | J35: - | K35: - | L35: - | M35: - | O35: =SUM(C35:N35) -> 0
A36: 6.1.1 | B36: Documentación técnica consolidada | C36: - | D36: - | E36: - | F36: - | G36: - | H36: - | I36: - | J36: - | K36: - | L36: - | M36: - | O36: =SUM(C36:N36) -> 0
A37: 6.1.2.1 | B37: Diapositivas de contexto y metodología | L37: 2500 | M37: 2500 | N37: 2500 | O37: =SUM(C37:N37) -> 7500
A38: 6.1.2.2 | B38: Narrativa ejecutiva y resultados | M38: 2500 | N38: 5000 | O38: =SUM(C38:N38) -> 7500
A48: TOTAL | C48: =SUM(C9:C47) -> 17081 | D48: =SUM(D9:D47) -> 1553 | E48: =SUM(E9:E47) -> 3153 | F48: =SUM(F9:F47) -> 26445 | G48: =SUM(G9:G47) -> 23292 | H48: =SUM(H9:H47) -> 38820 | I48: =SUM(I9:I47) -> 38820 | J48: =SUM(J9:J47) -> 40373 | ... O48: =SUM(O9:O47) -> 258790 | P48: =SUM(P10:P47) -> 0 | Q48: =SUM(Q10:Q47) -> 0 | R48: =SUM(R10:R47) -> 0 | S48: =SUM(S10:S47) -> 0 | T48: =SUM(T10:T47) -> 0 | U48: =SUM(U10:U47) -> 0 | V48: =SUM(V10:V47) -> 0 | W48: =SUM(W10:W47) -> 0 | ... BJ48: =SUM(BJ10:BJ47) -> 0

Sheet Ejemplo
C7: Curva S de Recursos
C9: Proyecto: | D9: Segmentación de mercado para Targeting
C10: ID: | D10: SMT-2026-01
C11: Fecha de Inicio | D11: 16/Feb/2026 | F11: Fecha Fin: | H11: 09/May/2026 | K11: Fecha de Corte: | M11: 18/Feb/2026
D13: 2026 – Semanas del Proyecto
D14: Sem 1 | E14: Sem 2 | F14: Sem 3 | G14: Sem 4 | H14: Sem 5 | I14: Sem 6 | J14: Sem 7 | K14: Sem 8 | L14: Sem 9 | M14: Sem 10 | N14: Sem 11 | O14: Sem 12
C15: Valor Planificado | D15: ='Detalle de Costos'!C48 -> 17081 | E15: ='Detalle de Costos'!D48 -> 1553 | F15: ='Detalle de Costos'!E48 -> 3153 | G15: ='Detalle de Costos'!F48 -> 26445 | H15: ='Detalle de Costos'!G48 -> 23292 | I15: ='Detalle de Costos'!H48 -> 38820 | J15: ='Detalle de Costos'!I48 -> 38820 | K15: ='Detalle de Costos'!J48 -> 40373 | ... O15: ='Detalle de Costos'!N48 -> 7500
C16: Valor Planificado Acumulado | D16: =D15 -> 17081 | E16: =D16+E15 -> 18634 | F16: =E16+F15 -> 21787 | G16: =F16+G15 -> 48232 | H16: =G16+H15 -> 71524 | I16: =H16+I15 -> 110344 | J16: =I16+J15 -> 149164 | K16: =J16+K15 -> 189537 | L16: =K16+L15 -> 222146 | ... O16: =N16+O15 -> 265096
C17: Costo Real ($MXN) – SIMULADO | D17: 4969 | E17: 6211 | F17: 6211 | G17: 6211 | H17: 5590 | I17: 6832 | J17: 7453 | K17: 8696 | L17: 9317 | M17: 9317 | N17: 8696 | O17: 220497
C18: Costo Real Acumulado | D18: =D17 -> 4969 | E18: =D18+E17 -> 11180 | F18: =E18+F17 -> 17391 | G18: =F18+G17 -> 23602 | H18: =G18+H17 -> 29192 | I18: =H18+I17 -> 36024 | J18: =I18+J17 -> 43477 | K18: =J18+K17 -> 52173 | L18: =K18+L17 -> 61490 | ... O18: =N18+O17 -> 300000
C20: ⚠ Presupuesto total: $300,000 MXN | Costo Real SIMULADO — reemplazar con valores reales al cerrar cada semana.
